Workbook

Sheet Dirty Data
B2: Date | C2: Client | D2: Contact | E2: Department | F2: Payment | G2: Revenue | H2: Profit | I2: Profit Margin
B3: 45076 | C3: AMAZON.COM, INC. (XNAS:AMZN) | D3: Bill SmITH | E3: Cloud Tech_Texas | F3: Transfer | G3: 4500 | H3: 598 | I3: =H3/G3 -> 0.13288889
B4: 45076 | C4: TESLA, INC. (XNAS:TSLA) | D4: KEN Singh | E4: Strategy_New York | F4: PayPal | G4: 3800 | H4: 1045 | I4: =H4/G4 -> 0.275
B5: 45076 | C5: NETFLIX, INC. (XNAS:NFLX) | D5: Harley Fritz | E5: Strategy_New York | G5: 3712.5 | H5: 1009 | I5: =H5/G5 -> 0.27178451
B6: 45076 | C6: THE PROCTER & GAMBLE COMPANY (XNYS:PG) | D6: Nyla Novak | E6: Operations_Florida | H6: 779 | I6: =H6/G6 -> #DIV/0!
B7: 45076 | C7: THE GOLDMAN SACHS GROUP, INC. (XNYS:GS) | D7: David Rasmussen | E7: Operations_Florida | F7: Check | G7: 5000 | H7: 684 | I7: =H7/G7 -> 0.1368
B8: 45077 | C8: JPMORGAN CHASE & CO. (XNYS:JPM) | D8: IVAN HINEY | E8: Cloud Tech_Texas | F8: Transfer | G8: 6100 | H8: 544 | I8: =H8/G8 -> 0.089180328
B9: 45077 | C9: MORGAN STANLEY (XNYS:MS) | D9: JONha Ma | E9: Cloud Tech_Texas | F9: Transfer | G9: 4625 | H9: 670 | I9: =H9/G9 -> 0.14486486
B10: 45077 | C10: CITIGROUP INC. (XNYS:C) | D10: Jordan Boone | E10: Cloud Tech_Texas | F10: Transfer | G10: 3800 | H10: 2045 | I10: =H10/G10 -> 0.53815789
B11: 45077 | C11: BANK OF AMERICA CORPORATION (XNYS:BAC) | D11: Kylee Townsend | E11: Cloud Tech_Texas | F11: Card | G11: 3600 | H11: 1564 | I11: =H11/G11 -> 0.43444444
B12: 45077 | C12: WALMART INC. (XNYS:WMT) | D12: Nora Rollins | E12: Cloud Tech_Texas | F12: Check | G12: 5100 | H12: 1220 | I12: =H12/G12 -> 0.23921569
B13: 45077 | C13: TARGET CORPORATION (XNYS:TGT) | D13: BRENDAN Wallace | E13: Cloud Tech_Texas | F13: Check | G13: 4750 | H13: 1435 | I13: =H13/G13 -> 0.30210526
B14: 45077 | C14: COSTCO WHOLESALE CORPORATION (XNAS:COST) | D14: Conor Wise | E14: Operations_Florida | F14: Transfer | G14: 6000 | H14: 998 | I14: =H14/G14 -> 0.16633333
B15: 45077 | C15: MCDONALD'S CORPORATION (XNYS:MCD) | D15: Steven MIChael | E15: Big Data_California | F15: Check | G15: 4500 | H15: 780 | I15: =H15/G15 -> 0.17333333
B16: 45078 | C16: EXXON MOBIL CORPORATION (XNYS:XOM) | D16: Lucia Mckay | E16: Big Data_California | F16: Card | H16: 1044 | I16: =H16/G16 -> #DIV/0!
B17: 45078 | C17: VERIZON COMMUNICATIONS INC. (XNYS:VZ) | D17: JoSE Roach | E17: Big Data_California | F17: Transfer | G17: 3712.5 | H17: 1222 | I17: =H17/G17 -> 0.32915825
B18: 45078 | C18: THE HOME DEPOT, INC. (XNYS:HD) | D18: Franklin WRIGT | E18: Big Data_California | F18: Transfer | G18: 4950 | H18: 1065 | I18: =H18/G18 -> 0.21515152
B19: 45078 | C19: CISCO SYSTEMS, INC. (XNAS:CSCO) | D19: Alia Thornton | E19: Operations_Florida | F19: Transfer | G19: 4750 | H19: 810 | I19: =H19/G19 -> 0.17052632
B20: 45078 | C20: CHEVRON CORPORATION (XNYS:CVX) | D20: Denzel Flores | E20: Operations_Florida | F20: Transfer | G20: 7320 | H20: 933 | I20: =H20/G20 -> 0.12745902
B21: 45077 | C21: COSTCO WHOLESALE CORPORATION (XNAS:COST) | D21: Conor Wise | E21: Operations_Florida | F21: Transfer | G21: 6000 | H21: 998 | I21: =H21/G21 -> 0.16633333
B22: 45077 | C22: MCDONALD'S CORPORATION (XNYS:MCD) | D22: Steven MIChael | E22: Big Data_California | F22: Check | G22: 4500 | H22: 780 | I22: =H22/G22 -> 0.17333333
B23: 45078 | C23: AT&T INC. (XNYS:T) | D23: Bruno CordOVA | E23: Big Data_California | F23: Transfer | G23: 5087.5 | H23: 655 | I23: =H23/G23 -> 0.12874693
B24: 45078 | C24: INTEL CORPORATION (XNAS:INTC) | D24: jaylynn napp | E24: Big Data_California | F24: Transfer | G24: 4500 | H24: 722 | I24: =H24/G24 -> 0.16044444
B25: 45078 | C25: GENERAL MOTORS COMPANY (XNYS:GM) | D25: Bruce RICH | E25: Big Data_California | F25: Card | G25: 4250 | H25: 901 | I25: =H25/G25 -> 0.212
B26: 45079 | C26: MICROSOFT CORPORATION (XNAS:MSFT) | D26: Arturo Moore | E26: Big Data_California | F26: PayPal | G26: 5250 | H26: 1349 | I26: =H26/G26 -> 0.25695238
B27: 45079 | C27: COMCAST CORPORATION (XNAS:CMCSA) | D27: Bryce Carpenter | E27: Strategy_New York | F27: PayPal | G27: 6500 | H27: 1288 | I27: =H27/G27 -> 0.19815385
B28: 45079 | C28: DELL TECHNOLOGIES INC. (XNYS:DELL) | D28: Jaidyn ANDERSEN | E28: Strategy_New York | F28: PayPal | G28: 7500 | H28: 1664 | I28: =H28/G28 -> 0.22186667
... B33: 45076 | C33: THE GOLDMAN SACHS GROUP, INC. (XNYS:GS) | D33: David Rasmussen | E33: Operations_Florida | F33: Check | G33: 5000 | H33: 684 | I33: =H33/G33 -> 0.1368

Sheet Clean
A1: Trans_ID | B1: Date | C1: Client_ID | D1: Client | E1: First Name | F1: Last Name | G1: Dept_ID | H1: Department | I1: State_ID | J1: State | K1: Payment_ID | L1: Payment | M1: Revenue | N1: Profit | O1: Profit Margin
A2: T-101 | B2: 45076 | C2: =VLOOKUP(D2,Client!A$3:B$30,2,TRUE ) -> C-100 | D2: AMAZON.COM, INC. | E2: Bill | F2: Smith | G2: =VLOOKUP(H2,Department!A$3:B$6,2,TRUE) -> D-102 | H2: Cloud Tech | I2: =VLOOKUP(J2,State!A$3:B$6,2,TRUE) -> S-104 | J2: Texas | K2: =VLOOKUP(L2,Payment!A$3:B$7,2,TRUE) -> P-105 | L2: Transfer | M2: 4500 | N2: 598 | O2: =IFERROR(N2/M2, 0) -> 0.13288889
A3: T-102 | B3: 45076 | C3: =VLOOKUP(D3,Client!A$3:B$30,2,TRUE ) -> C-122 | D3: TESLA, INC. | E3: Ken | F3: Singh | G3: =VLOOKUP(H3,Department!A$3:B$6,2,TRUE) -> D-104 | H3: Strategy | I3: =VLOOKUP(J3,State!A$3:B$6,2,TRUE) -> S-103 | J3: New York | K3: =VLOOKUP(L3,Payment!A$3:B$7,2,TRUE) -> P-104 | L3: PayPal | M3: 3800 | N3: 1045 | O3: =IFERROR(N3/M3, 0) -> 0.275
A4: T-103 | B4: 45076 | C4: =VLOOKUP(D4,Client!A$3:B$30,2,TRUE ) -> C-120 | D4: NETFLIX, INC. | E4: Harley | F4: Fritz | G4: =VLOOKUP(H4,Department!A$3:B$6,2,TRUE) -> D-104 | H4: Strategy | I4: =VLOOKUP(J4,State!A$3:B$6,2,TRUE) -> S-103 | J4: New York | K4: =VLOOKUP(L4,Payment!A$3:B$7,2,TRUE) -> P-103 | L4: Other | M4: 3712.5 | N4: 1009 | O4: =IFERROR(N4/M4, 0) -> 0.27178451
A5: T-104 | B5: 45076 | C5: =VLOOKUP(D5,Client!A$3:B$30,2,TRUE ) -> C-125 | D5: THE PROCTER & GAMBLE COMPANY | E5: Nyla | F5: Novak | G5: =VLOOKUP(H5,Department!A$3:B$6,2,TRUE) -> D-103 | H5: Operations | I5: =VLOOKUP(J5,State!A$3:B$6,2,TRUE) -> S-102 | J5: Florida | K5: =VLOOKUP(L5,Payment!A$3:B$7,2,TRUE) -> P-103 | L5: Other | M5: 4994 | N5: 779 | O5: =IFERROR(N5/M5, 0) -> 0.15598718
A6: T-105 | B6: 45076 | C6: =VLOOKUP(D6,Client!A$3:B$30,2,TRUE ) -> C-123 | D6: THE GOLDMAN SACHS GROUP, INC. | E6: David | F6: Rasmussen | G6: =VLOOKUP(H6,Department!A$3:B$6,2,TRUE) -> D-103 | H6: Operations | I6: =VLOOKUP(J6,State!A$3:B$6,2,TRUE) -> S-102 | J6: Florida | K6: =VLOOKUP(L6,Payment!A$3:B$7,2,TRUE) -> P-102 | L6: Check | M6: 5000 | N6: 684 | O6: =IFERROR(N6/M6, 0) -> 0.1368
A7: T-106 | B7: 45077 | C7: =VLOOKUP(D7,Client!A$3:B$30,2,TRUE ) -> C-115 | D7: JPMORGAN CHASE & CO. | E7: Ivan | F7: Hiney | G7: =VLOOKUP(H7,Department!A$3:B$6,2,TRUE) -> D-102 | H7: Cloud Tech | I7: =VLOOKUP(J7,State!A$3:B$6,2,TRUE) -> S-104 | J7: Texas | K7: =VLOOKUP(L7,Payment!A$3:B$7,2,TRUE) -> P-105 | L7: Transfer | M7: 6100 | N7: 544 | O7: =IFERROR(N7/M7, 0) -> 0.089180328
A8: T-107 | B8: 45077 | C8: =VLOOKUP(D8,Client!A$3:B$30,2,TRUE ) -> C-119 | D8: MORGAN STANLEY | E8: Jonha | F8: Ma | G8: =VLOOKUP(H8,Department!A$3:B$6,2,TRUE) -> D-102 | H8: Cloud Tech | I8: =VLOOKUP(J8,State!A$3:B$6,2,TRUE) -> S-104 | J8: Texas | K8: =VLOOKUP(L8,Payment!A$3:B$7,2,TRUE) -> P-105 | L8: Transfer | M8: 4625 | N8: 670 | O8: =IFERROR(N8/M8, 0) -> 0.14486486
A9: T-108 | B9: 45077 | C9: =VLOOKUP(D9,Client!A$3:B$30,2,TRUE ) -> C-105 | D9: CITIGROUP INC. | E9: Jordan | F9: Boone | G9: =VLOOKUP(H9,Department!A$3:B$6,2,TRUE) -> D-102 | H9: Cloud Tech | I9: =VLOOKUP(J9,State!A$3:B$6,2,TRUE) -> S-104 | J9: Texas | K9: =VLOOKUP(L9,Payment!A$3:B$7,2,TRUE) -> P-105 | L9: Transfer | M9: 3800 | N9: 2045 | O9: =IFERROR(N9/M9, 0) -> 0.53815789
A10: T-109 | B10: 45077 | C10: =VLOOKUP(D10,Client!A$3:B$30,2,TRUE ) -> C-102 | D10: BANK OF AMERICA CORPORATION | E10: Kylee | F10: Townsend | G10: =VLOOKUP(H10,Department!A$3:B$6,2,TRUE) -> D-102 | H10: Cloud Tech | I10: =VLOOKUP(J10,State!A$3:B$6,2,TRUE) -> S-104 | J10: Texas | K10: =VLOOKUP(L10,Payment!A$3:B$7,2,TRUE) -> P-101 | L10: Card | M10: 3600 | N10: 1564 | O10: =IFERROR(N10/M10, 0) -> 0.43444444
A11: T-110 | B11: 45077 | C11: =VLOOKUP(D11,Client!A$3:B$30,2,TRUE ) -> C-127 | D11: WALMART INC. | E11: Nora | F11: Rollins | G11: =VLOOKUP(H11,Department!A$3:B$6,2,TRUE) -> D-102 | H11: Cloud Tech | I11: =VLOOKUP(J11,State!A$3:B$6,2,TRUE) -> S-104 | J11: Texas | K11: =VLOOKUP(L11,Payment!A$3:B$7,2,TRUE) -> P-102 | L11: Check | M11: 5100 | N11: 1220 | O11: =IFERROR(N11/M11, 0) -> 0.23921569
A12: T-111 | B12: 45077 | C12: =VLOOKUP(D12,Client!A$3:B$30,2,TRUE ) -> C-121 | D12: TARGET CORPORATION | E12: Brendan | F12: Wallace | G12: =VLOOKUP(H12,Department!A$3:B$6,2,TRUE) -> D-102 | H12: Cloud Tech | I12: =VLOOKUP(J12,State!A$3:B$6,2,TRUE) -> S-104 | J12: Texas | K12: =VLOOKUP(L12,Payment!A$3:B$7,2,TRUE) -> P-102 | L12: Check | M12: 4750 | N12: 1435 | O12: =IFERROR(N12/M12, 0) -> 0.30210526
A13: T-112 | B13: 45077 | C13: =VLOOKUP(D13,Client!A$3:B$30,2,TRUE ) -> C-107 | D13: COSTCO WHOLESALE CORPORATION | E13: Conor | F13: Wise | G13: =VLOOKUP(H13,Department!A$3:B$6,2,TRUE) -> D-103 | H13: Operations | I13: =VLOOKUP(J13,State!A$3:B$6,2,TRUE) -> S-102 | J13: Florida | K13: =VLOOKUP(L13,Payment!A$3:B$7,2,TRUE) -> P-105 | L13: Transfer | M13: 6000 | N13: 998 | O13: =IFERROR(N13/M13, 0) -> 0.16633333
... A29: T-128 | B29: 45079 | C29: =VLOOKUP(D29,Client!A$3:B$30,2,TRUE ) -> C-116 | D29: LOCKHEED MARTIN CORPORATION | E29: Mik | F29: Naam | G29: =VLOOKUP(H29,Department!A$3:B$6,2,TRUE) -> D-104 | H29: Strategy | I29: =VLOOKUP(J29,State!A$3:B$6,2,TRUE) -> S-103 | J29: New York | K29: =VLOOKUP(L29,Payment!A$3:B$7,2,TRUE) -> P-101 | L29: Card | M29: 5400 | N29: 540 | O29: =IFERROR(N29/M29, 0) -> 0.1

Sheet Payment
A2: Payment | B2: Payment_Id
A3: Card | B3: P-101
A4: Check | B4: P-102
A5: Other | B5: P-103
A6: PayPal | B6: P-104
A7: Transfer | B7: P-105

Sheet State
A2: State | B2: State_Id
A3: California | B3: S-101
A4: Florida | B4: S-102
A5: New York | B5: S-103
A6: Texas | B6: S-104

Sheet Department
A2: Department | B2: Dept_Id
A3: Big Data | B3: D-101
A4: Cloud Tech | B4: D-102
A5: Operations | B5: D-103
A6: Strategy | B6: D-104

Sheet Client
A2: Client | B2: Client_Id | C2: First Name | D2: Last Name
A3: AMAZON.COM, INC. | B3: C-100 | C3: Bill | D3: Smith
A4: AT&T INC. | B4: C-101 | C4: Bruno | D4: Cordova
A5: BANK OF AMERICA CORPORATION | B5: C-102 | C5: Kylee | D5: Townsend
A6: CHEVRON CORPORATION | B6: C-103 | C6: Denzel | D6: Flores
A7: CISCO SYSTEMS, INC. | B7: C-104 | C7: Alia | D7: Thornton
A8: CITIGROUP INC. | B8: C-105 | C8: Jordan | D8: Boone
A9: COMCAST CORPORATION | B9: C-106 | C9: Bryce | D9: Carpenter
A10: COSTCO WHOLESALE CORPORATION | B10: C-107 | C10: Conor | D10: Wise
A11: DELL TECHNOLOGIES INC. | B11: C-108 | C11: Jaidyn | D11: Andersen
A12: EXXON MOBIL CORPORATION | B12: C-109 | C12: Lucia | D12: Mckay
A13: FEDEX CORPORATION | B13: C-110 | C13: Harry | D13: Lee
... A30: WALMART INC. | B30: C-127 | C30: Nora | D30: Rollins
